name_of_package/__init__.py
name_of_package-0.0.1.dist-info/METADATA
name_of_package-0.0.1.dist-info/WHEEL
name_of_package-0.0.1.dist-info/licenses/LICENSE
name_of_package-0.0.1.dist-info/RECORD
